{"vod_id": 2136045986, "stream_id": 0, "title": "\u3010\u5b8c\u5168\u521d\u898b\u3011\u30e9\u30a4\u30d5\u30a4\u30ba\u30b9\u30c8\u30ec\u30f3\u30b8\uff033\u3010\u30cd\u30bf\u30d0\u30ec\u7981\u6b62\u3011", "description": null, "created_at": "2024-05-03 08:22:23", "published_at": "2024-05-03 08:22:23", "thumbnail_url": "https://static-cdn.jtvnw.net/cf_vods/d3vd9lfkzbru3h/10b12611c8b275d2aeba_gero_kinjo_41268998455_1714724538//thumb/thumb0-90x60.jpg", "duration": 20109, "chat_archived": true, "video_archived": false}