{"vod_id": 583979582, "stream_id": 0, "title": "4/5/2020 \u30b9\u30c8\uff15\uff06\u30c0\u30c3\u30af\u30bd\u30a6\u30eb\uff0fStreet Fighter V & Duck Souls", "description": null, "created_at": "2020-04-05 13:37:48", "published_at": "2020-04-05 13:37:48", "thumbnail_url": "https://static-cdn.jtvnw.net/cf_vods/d2nvs31859zcd8/dbc3ecf7ea6bc457f43d_daigothebeastv_37396107424_1406064194/thumb/custom-acdde047-46f1-455b-bc67-2201b9cb47ba-90x60.jpeg", "duration": 14441, "chat_archived": true, "video_archived": false}