{"vod_id": 660007855, "stream_id": 0, "title": "\u3010\u65ad\u8178\u306e\u601d\u3044\u3011\u30db\u30e9\u30b2\u30fc(\u3074\u3048\u3093)\u3084\u308a\u307e\u3059\u3010\u82e6\u6e0b\u306e\u6c7a\u65ad\u3011", "description": null, "created_at": "2020-06-24 10:53:08", "published_at": "2020-06-24 10:53:08", "thumbnail_url": "https://static-cdn.jtvnw.net/cf_vods/d2nvs31859zcd8/87031a05de2f8fb28f06_raderaderader_38866447904_1498111157//thumb/thumb0-90x60.jpg", "duration": 1667, "chat_archived": true, "video_archived": false}